{"__symbolic":"module","version":1,"metadata":{"ConferenceApp":{"__symbolic":"class","decorators":[{"__symbolic":"call","expression":{"__symbolic":"reference","module":"@angular/core","name":"Component"},"arguments":[{"templateUrl":"app.template.html"}]}],"members":{"nav":[{"__symbolic":"property","decorators":[{"__symbolic":"call","expression":{"__symbolic":"reference","module":"@angular/core","name":"ViewChild"},"arguments":[{"__symbolic":"reference","module":"ionic-angular","name":"Nav"}]}]}],"__ctor__":[{"__symbolic":"constructor","parameters":[{"__symbolic":"reference","module":"ionic-angular","name":"Events"},{"__symbolic":"reference","module":"../providers/user-data","name":"UserData"},{"__symbolic":"reference","module":"ionic-angular","name":"MenuController"},{"__symbolic":"reference","module":"ionic-angular","name":"Platform"},{"__symbolic":"reference","module":"../providers/conference-data","name":"ConferenceData"}]}],"openPage":[{"__symbolic":"method"}],"listenToLoginEvents":[{"__symbolic":"method"}],"enableMenu":[{"__symbolic":"method"}]}}}}